{"nodes": [{"id": "c_wsgta_universal_or_strategy_tests_ninjatrader_mocks_cs", "label": "NinjaTrader.Mocks.cs", "file_type": "code", "source_file": "C:\\WSGTA\\universal-or-strategy\\tests\\NinjaTrader.Mocks.cs", "source_location": "L1"}, {"id": "ninjatrader_mocks_ninjatrader_cbi", "label": "NinjaTrader.Cbi", "file_type": "code", "source_file": "C:\\WSGTA\\universal-or-strategy\\tests\\NinjaTrader.Mocks.cs", "source_location": "L12"}, {"id": "ninjatrader_mocks_account", "label": "Account", "file_type": "code", "source_file": "C:\\WSGTA\\universal-or-strategy\\tests\\NinjaTrader.Mocks.cs", "source_location": "L18"}, {"id": "ninjatrader_mocks_instrument", "label": "Instrument", "file_type": "code", "source_file": "C:\\WSGTA\\universal-or-strategy\\tests\\NinjaTrader.Mocks.cs", "source_location": "L19"}, {"id": "ninjatrader_mocks_order", "label": "Order", "file_type": "code", "source_file": "C:\\WSGTA\\universal-or-strategy\\tests\\NinjaTrader.Mocks.cs", "source_location": "L20"}, {"id": "ninjatrader_mocks_execution", "label": "Execution", "file_type": "code", "source_file": "C:\\WSGTA\\universal-or-strategy\\tests\\NinjaTrader.Mocks.cs", "source_location": "L21"}, {"id": "ninjatrader_mocks_ninjatrader_gui", "label": "NinjaTrader.Gui", "file_type": "code", "source_file": "C:\\WSGTA\\universal-or-strategy\\tests\\NinjaTrader.Mocks.cs", "source_location": "L24"}, {"id": "ninjatrader_mocks_ninjatrader_gui_chart", "label": "NinjaTrader.Gui.Chart", "file_type": "code", "source_file": "C:\\WSGTA\\universal-or-strategy\\tests\\NinjaTrader.Mocks.cs", "source_location": "L25"}, {"id": "ninjatrader_mocks_ninjatrader_gui_tools", "label": "NinjaTrader.Gui.Tools", "file_type": "code", "source_file": "C:\\WSGTA\\universal-or-strategy\\tests\\NinjaTrader.Mocks.cs", "source_location": "L26"}, {"id": "ninjatrader_mocks_ninjatrader_data", "label": "NinjaTrader.Data", "file_type": "code", "source_file": "C:\\WSGTA\\universal-or-strategy\\tests\\NinjaTrader.Mocks.cs", "source_location": "L27"}, {"id": "ninjatrader_mocks_ninjatrader_ninjascript", "label": "NinjaTrader.NinjaScript", "file_type": "code", "source_file": "C:\\WSGTA\\universal-or-strategy\\tests\\NinjaTrader.Mocks.cs", "source_location": "L28"}, {"id": "ninjatrader_mocks_ninjatrader_ninjascript_drawingtools", "label": "NinjaTrader.NinjaScript.DrawingTools", "file_type": "code", "source_file": "C:\\WSGTA\\universal-or-strategy\\tests\\NinjaTrader.Mocks.cs", "source_location": "L29"}, {"id": "ninjatrader_mocks_ninjatrader_ninjascript_indicators", "label": "NinjaTrader.NinjaScript.Indicators", "file_type": "code", "source_file": "C:\\WSGTA\\universal-or-strategy\\tests\\NinjaTrader.Mocks.cs", "source_location": "L30"}, {"id": "ninjatrader_mocks_ninjatrader_ninjascript_strategies", "label": "NinjaTrader.NinjaScript.Strategies", "file_type": "code", "source_file": "C:\\WSGTA\\universal-or-strategy\\tests\\NinjaTrader.Mocks.cs", "source_location": "L32"}, {"id": "ninjatrader_mocks_strategy", "label": "Strategy", "file_type": "code", "source_file": "C:\\WSGTA\\universal-or-strategy\\tests\\NinjaTrader.Mocks.cs", "source_location": "L34"}, {"id": "ninjatrader_mocks_strategy_print", "label": ".Print()", "file_type": "code", "source_file": "C:\\WSGTA\\universal-or-strategy\\tests\\NinjaTrader.Mocks.cs", "source_location": "L37"}, {"id": "ninjatrader_mocks_strategy_setrmaanchorfromipc", "label": ".SetRmaAnchorFromIpc()", "file_type": "code", "source_file": "C:\\WSGTA\\universal-or-strategy\\tests\\NinjaTrader.Mocks.cs", "source_location": "L58"}, {"id": "ninjatrader_mocks_strategy_markdispatchsyncpending", "label": ".MarkDispatchSyncPending()", "file_type": "code", "source_file": "C:\\WSGTA\\universal-or-strategy\\tests\\NinjaTrader.Mocks.cs", "source_location": "L59"}, {"id": "ninjatrader_mocks_strategy_addexpectedpositiondeltalocked", "label": ".AddExpectedPositionDeltaLocked()", "file_type": "code", "source_file": "C:\\WSGTA\\universal-or-strategy\\tests\\NinjaTrader.Mocks.cs", "source_location": "L60"}, {"id": "ninjatrader_mocks_strategy_enqueue", "label": ".Enqueue()", "file_type": "code", "source_file": "C:\\WSGTA\\universal-or-strategy\\tests\\NinjaTrader.Mocks.cs", "source_location": "L61"}, {"id": "ninjatrader_mocks_modeconfigprofile", "label": "ModeConfigProfile", "file_type": "code", "source_file": "C:\\WSGTA\\universal-or-strategy\\tests\\NinjaTrader.Mocks.cs", "source_location": "L63"}, {"id": "ninjatrader_mocks_targetsnapshot", "label": "TargetSnapshot", "file_type": "code", "source_file": "C:\\WSGTA\\universal-or-strategy\\tests\\NinjaTrader.Mocks.cs", "source_location": "L70"}, {"id": "ninjatrader_mocks_v12_002", "label": "V12_002", "file_type": "code", "source_file": "C:\\WSGTA\\universal-or-strategy\\tests\\NinjaTrader.Mocks.cs", "source_location": "L74"}, {"id": "ninjatrader_mocks_ninjatraderextensions", "label": "NinjaTraderExtensions", "file_type": "code", "source_file": "C:\\WSGTA\\universal-or-strategy\\tests\\NinjaTrader.Mocks.cs", "source_location": "L81"}, {"id": "ninjatrader_mocks_ninjatraderextensions_roundtoticksize", "label": ".RoundToTickSize()", "file_type": "code", "source_file": "C:\\WSGTA\\universal-or-strategy\\tests\\NinjaTrader.Mocks.cs", "source_location": "L83"}], "edges": [{"source": "c_wsgta_universal_or_strategy_tests_ninjatrader_mocks_cs", "target": "system", "relation": "imports", "confidence": "EXTRACTED", "source_file": "C:\\WSGTA\\universal-or-strategy\\tests\\NinjaTrader.Mocks.cs", "source_location": "L7", "weight": 1.0}, {"source": "c_wsgta_universal_or_strategy_tests_ninjatrader_mocks_cs", "target": "concurrent", "relation": "imports", "confidence": "EXTRACTED", "source_file": "C:\\WSGTA\\universal-or-strategy\\tests\\NinjaTrader.Mocks.cs", "source_location": "L8", "weight": 1.0}, {"source": "c_wsgta_universal_or_strategy_tests_ninjatrader_mocks_cs", "target": "generic", "relation": "imports", "confidence": "EXTRACTED", "source_file": "C:\\WSGTA\\universal-or-strategy\\tests\\NinjaTrader.Mocks.cs", "source_location": "L9", "weight": 1.0}, {"source": "c_wsgta_universal_or_strategy_tests_ninjatrader_mocks_cs", "target": "globalization", "relation": "imports", "confidence": "EXTRACTED", "source_file": "C:\\WSGTA\\universal-or-strategy\\tests\\NinjaTrader.Mocks.cs", "source_location": "L10", "weight": 1.0}, {"source": "c_wsgta_universal_or_strategy_tests_ninjatrader_mocks_cs", "target": "ninjatrader_mocks_ninjatrader_cbi", "relation": "contains", "confidence": "EXTRACTED", "source_file": "C:\\WSGTA\\universal-or-strategy\\tests\\NinjaTrader.Mocks.cs", "source_location": "L12", "weight": 1.0}, {"source": "c_wsgta_universal_or_strategy_tests_ninjatrader_mocks_cs", "target": "ninjatrader_mocks_account", "relation": "contains", "confidence": "EXTRACTED", "source_file": "C:\\WSGTA\\universal-or-strategy\\tests\\NinjaTrader.Mocks.cs", "source_location": "L18", "weight": 1.0}, {"source": "c_wsgta_universal_or_strategy_tests_ninjatrader_mocks_cs", "target": "ninjatrader_mocks_instrument", "relation": "contains", "confidence": "EXTRACTED", "source_file": "C:\\WSGTA\\universal-or-strategy\\tests\\NinjaTrader.Mocks.cs", "source_location": "L19", "weight": 1.0}, {"source": "c_wsgta_universal_or_strategy_tests_ninjatrader_mocks_cs", "target": "ninjatrader_mocks_order", "relation": "contains", "confidence": "EXTRACTED", "source_file": "C:\\WSGTA\\universal-or-strategy\\tests\\NinjaTrader.Mocks.cs", "source_location": "L20", "weight": 1.0}, {"source": "c_wsgta_universal_or_strategy_tests_ninjatrader_mocks_cs", "target": "ninjatrader_mocks_execution", "relation": "contains", "confidence": "EXTRACTED", "source_file": "C:\\WSGTA\\universal-or-strategy\\tests\\NinjaTrader.Mocks.cs", "source_location": "L21", "weight": 1.0}, {"source": "c_wsgta_universal_or_strategy_tests_ninjatrader_mocks_cs", "target": "ninjatrader_mocks_ninjatrader_gui", "relation": "contains", "confidence": "EXTRACTED", "source_file": "C:\\WSGTA\\universal-or-strategy\\tests\\NinjaTrader.Mocks.cs", "source_location": "L24", "weight": 1.0}, {"source": "c_wsgta_universal_or_strategy_tests_ninjatrader_mocks_cs", "target": "ninjatrader_mocks_ninjatrader_gui_chart", "relation": "contains", "confidence": "EXTRACTED", "source_file": "C:\\WSGTA\\universal-or-strategy\\tests\\NinjaTrader.Mocks.cs", "source_location": "L25", "weight": 1.0}, {"source": "c_wsgta_universal_or_strategy_tests_ninjatrader_mocks_cs", "target": "ninjatrader_mocks_ninjatrader_gui_tools", "relation": "contains", "confidence": "EXTRACTED", "source_file": "C:\\WSGTA\\universal-or-strategy\\tests\\NinjaTrader.Mocks.cs", "source_location": "L26", "weight": 1.0}, {"source": "c_wsgta_universal_or_strategy_tests_ninjatrader_mocks_cs", "target": "ninjatrader_mocks_ninjatrader_data", "relation": "contains", "confidence": "EXTRACTED", "source_file": "C:\\WSGTA\\universal-or-strategy\\tests\\NinjaTrader.Mocks.cs", "source_location": "L27", "weight": 1.0}, {"source": "c_wsgta_universal_or_strategy_tests_ninjatrader_mocks_cs", "target": "ninjatrader_mocks_ninjatrader_ninjascript", "relation": "contains", "confidence": "EXTRACTED", "source_file": "C:\\WSGTA\\universal-or-strategy\\tests\\NinjaTrader.Mocks.cs", "source_location": "L28", "weight": 1.0}, {"source": "c_wsgta_universal_or_strategy_tests_ninjatrader_mocks_cs", "target": "ninjatrader_mocks_ninjatrader_ninjascript_drawingtools", "relation": "contains", "confidence": "EXTRACTED", "source_file": "C:\\WSGTA\\universal-or-strategy\\tests\\NinjaTrader.Mocks.cs", "source_location": "L29", "weight": 1.0}, {"source": "c_wsgta_universal_or_strategy_tests_ninjatrader_mocks_cs", "target": "ninjatrader_mocks_ninjatrader_ninjascript_indicators", "relation": "contains", "confidence": "EXTRACTED", "source_file": "C:\\WSGTA\\universal-or-strategy\\tests\\NinjaTrader.Mocks.cs", "source_location": "L30", "weight": 1.0}, {"source": "c_wsgta_universal_or_strategy_tests_ninjatrader_mocks_cs", "target": "ninjatrader_mocks_ninjatrader_ninjascript_strategies", "relation": "contains", "confidence": "EXTRACTED", "source_file": "C:\\WSGTA\\universal-or-strategy\\tests\\NinjaTrader.Mocks.cs", "source_location": "L32", "weight": 1.0}, {"source": "c_wsgta_universal_or_strategy_tests_ninjatrader_mocks_cs", "target": "ninjatrader_mocks_strategy", "relation": "contains", "confidence": "EXTRACTED", "source_file": "C:\\WSGTA\\universal-or-strategy\\tests\\NinjaTrader.Mocks.cs", "source_location": "L34", "weight": 1.0}, {"source": "ninjatrader_mocks_strategy", "target": "ninjatrader_mocks_strategy_print", "relation": "method", "confidence": "EXTRACTED", "source_file": "C:\\WSGTA\\universal-or-strategy\\tests\\NinjaTrader.Mocks.cs", "source_location": "L37", "weight": 1.0}, {"source": "ninjatrader_mocks_strategy", "target": "ninjatrader_mocks_strategy_setrmaanchorfromipc", "relation": "method", "confidence": "EXTRACTED", "source_file": "C:\\WSGTA\\universal-or-strategy\\tests\\NinjaTrader.Mocks.cs", "source_location": "L58", "weight": 1.0}, {"source": "ninjatrader_mocks_strategy", "target": "ninjatrader_mocks_strategy_markdispatchsyncpending", "relation": "method", "confidence": "EXTRACTED", "source_file": "C:\\WSGTA\\universal-or-strategy\\tests\\NinjaTrader.Mocks.cs", "source_location": "L59", "weight": 1.0}, {"source": "ninjatrader_mocks_strategy", "target": "ninjatrader_mocks_strategy_addexpectedpositiondeltalocked", "relation": "method", "confidence": "EXTRACTED", "source_file": "C:\\WSGTA\\universal-or-strategy\\tests\\NinjaTrader.Mocks.cs", "source_location": "L60", "weight": 1.0}, {"source": "ninjatrader_mocks_strategy", "target": "ninjatrader_mocks_strategy_enqueue", "relation": "method", "confidence": "EXTRACTED", "source_file": "C:\\WSGTA\\universal-or-strategy\\tests\\NinjaTrader.Mocks.cs", "source_location": "L61", "weight": 1.0}, {"source": "c_wsgta_universal_or_strategy_tests_ninjatrader_mocks_cs", "target": "ninjatrader_mocks_modeconfigprofile", "relation": "contains", "confidence": "EXTRACTED", "source_file": "C:\\WSGTA\\universal-or-strategy\\tests\\NinjaTrader.Mocks.cs", "source_location": "L63", "weight": 1.0}, {"source": "c_wsgta_universal_or_strategy_tests_ninjatrader_mocks_cs", "target": "ninjatrader_mocks_targetsnapshot", "relation": "contains", "confidence": "EXTRACTED", "source_file": "C:\\WSGTA\\universal-or-strategy\\tests\\NinjaTrader.Mocks.cs", "source_location": "L70", "weight": 1.0}, {"source": "c_wsgta_universal_or_strategy_tests_ninjatrader_mocks_cs", "target": "ninjatrader_mocks_v12_002", "relation": "contains", "confidence": "EXTRACTED", "source_file": "C:\\WSGTA\\universal-or-strategy\\tests\\NinjaTrader.Mocks.cs", "source_location": "L74", "weight": 1.0}, {"source": "ninjatrader_mocks_v12_002", "target": "ninjatrader_mocks_strategy", "relation": "inherits", "confidence": "EXTRACTED", "source_file": "C:\\WSGTA\\universal-or-strategy\\tests\\NinjaTrader.Mocks.cs", "source_location": "L74", "weight": 1.0}, {"source": "c_wsgta_universal_or_strategy_tests_ninjatrader_mocks_cs", "target": "ninjatrader_mocks_ninjatraderextensions", "relation": "contains", "confidence": "EXTRACTED", "source_file": "C:\\WSGTA\\universal-or-strategy\\tests\\NinjaTrader.Mocks.cs", "source_location": "L81", "weight": 1.0}, {"source": "ninjatrader_mocks_ninjatraderextensions", "target": "ninjatrader_mocks_ninjatraderextensions_roundtoticksize", "relation": "method", "confidence": "EXTRACTED", "source_file": "C:\\WSGTA\\universal-or-strategy\\tests\\NinjaTrader.Mocks.cs", "source_location": "L83", "weight": 1.0}], "raw_calls": [{"caller_nid": "ninjatrader_mocks_strategy_print", "callee": "WriteLine", "source_file": "C:\\WSGTA\\universal-or-strategy\\tests\\NinjaTrader.Mocks.cs", "source_location": "L37"}, {"caller_nid": "ninjatrader_mocks_strategy_enqueue", "callee": "a", "source_file": "C:\\WSGTA\\universal-or-strategy\\tests\\NinjaTrader.Mocks.cs", "source_location": "L61"}, {"caller_nid": "ninjatrader_mocks_ninjatraderextensions_roundtoticksize", "callee": "Round", "source_file": "C:\\WSGTA\\universal-or-strategy\\tests\\NinjaTrader.Mocks.cs", "source_location": "L85"}]}